metalog/__init__.py
metalog/metalog.py
metalog/support_func.py
metalog-0.2.2.dist-info/LICENSE
metalog-0.2.2.dist-info/METADATA
metalog-0.2.2.dist-info/WHEEL
metalog-0.2.2.dist-info/top_level.txt
metalog-0.2.2.dist-info/RECORD
