Metadata-Version: 2.1
Name: metalog
Version: 0.2.2
Summary: the package fits data to metalog distribution and generates samples, quantiles, densities and probabilities based on the fitted distribution.
Home-page: https://github.com/kimsergeo/metalog
Author: Sergey Kim, Reidar Brumer Bratvold
Author-email: kimsergeo@gmail.com, reidar.bratvold@uis.no
License: MIT
Platform: UNKNOWN
Classifier: Development Status :: 2 - Pre-Alpha
Classifier: License :: OSI Approved :: MIT License
Classifier: Programming Language :: Python
Classifier: Programming Language :: Python :: 3
Classifier: Programming Language :: Python :: 3.4
Classifier: Programming Language :: Python :: 3.5
Classifier: Programming Language :: Python :: 3.6
Classifier: Programming Language :: Python :: 3.7
